bzp/__init__.py
bzp/__version__.py
bzp-1.1.0.dist-info/LICENSE
bzp-1.1.0.dist-info/METADATA
bzp-1.1.0.dist-info/WHEEL
bzp-1.1.0.dist-info/top_level.txt
bzp-1.1.0.dist-info/RECORD
