Metadata-Version: 2.1
Name: bzp
Version: 1.1.0
Summary: Manager for bz2 pickle files
Home-page: https://github.com/ideascup/bzp/
Author: Dmitriy Pleshevskiy
Author-email: dmitriy@ideascup.me
License: MIT
Platform: UNKNOWN
